haot/__init__.py
haot/aerodynamics.py
haot/constants.py
haot/conversions.py
haot/optics.py
haot/quantum_mechanics.py
haot-1.1.3.dist-info/licenses/LICENSE
haot-1.1.3.dist-info/METADATA
haot-1.1.3.dist-info/WHEEL
haot-1.1.3.dist-info/entry_points.txt
haot-1.1.3.dist-info/top_level.txt
haot-1.1.3.dist-info/RECORD
